[
  {
    "author": "Anandhi G",
    "rating": 5,
    "review_text": "Well organized and good teaching",
    "relative_time": "5 months ago",
    "profile_image_url": "https://lh3.googleusercontent.com/a-/ALV-UdVdNiHKQwKKkWCIhKBIuQ9QdAmhfCKLqj1f029oJPDKk4IC4WI=w54-h54-p-rp-mo-br100"
  },
  {
    "author": "ganesh priya",
    "rating": 5,
    "review_text": "Very good academy 👍",
    "relative_time": "5 months ago",
    "profile_image_url": "https://lh3.googleusercontent.com/a-/ALV-UjXHeNQNo8kLhVsaDhCWEgFwSmU1ukMQ2dDt-6lonk1A1_3aPGgH=w54-h54-p-rp-mo-br100"
  },
  {
    "author": "Akshaya Sarathy",
    "rating": 5,
    "review_text": "Well organised place for students",
    "relative_time": "4 months ago",
    "profile_image_url": "https://lh3.googleusercontent.com/a/ACg8ocJI2VbSh7YkwJIk4toqiMIy1Ub33IcYZRpX4vf45U82rxkm0g=w54-h54-p-rp-mo-br100"
  },
  {
    "author": "Mohan Raj C025",
    "rating": 5,
    "review_text": "Sir! Intha markazhi masam mudiyira varaikum morning class venam sir morning kuluruthu athuku pathil evening one hour extra vechikonga aprm revision panna start pannunga sir lesson edukurathu pothum sir exam Kita vandhuduchu matha padi all are good sir thank u",
    "relative_time": "7 years ago",
    "profile_image_url": "https://lh3.googleusercontent.com/a-/ALV-UjX074wohzaLgj5qIgqSR8k2apXZuiK_XAdOTEMJh4jPk3HuU-Re=w54-h54-p-rp-mo-br100"
  },
  {
    "author": "VIJAYARANI R",
    "rating": 5,
    "review_text": "Best institution for all students",
    "relative_time": "5 months ago",
    "profile_image_url": "https://lh3.googleusercontent.com/a-/ALV-UjVnU9NIKV1Y4icot66XhX4trRRhniJ5LVB8cOtsBoSLxR3JWzc=w54-h54-p-rp-mo-br100"
  },
  {
    "author": "vetri selvan",
    "rating": 5,
    "review_text": "Good academy",
    "relative_time": "2 years ago",
    "profile_image_url": "https://lh3.googleusercontent.com/a-/ALV-UjWvki7tlvVoijVaEjqN0IJRJkutc-m2h65syaqKdlZkCq8oCi3V=w54-h54-p-rp-mo-br100"
  },
  {
    "author": "M.Shenbagavalli B.com.General",
    "rating": 5,
    "review_text": "Good and well trained teachers",
    "relative_time": "6 months ago",
    "profile_image_url": "https://lh3.googleusercontent.com/a/ACg8ocJEc9PSPU_XY0E9N5lr6FJMLqZ37RvcqyzFyeOyTwMYcqiEKQ=w54-h54-p-rp-mo-br100"
  },
  {
    "author": "Nios Aca",
    "rating": 5,
    "review_text": "This bb academy is really motivation for kids and help to learn and achieve their target i am also studying in that tuition i'ts really helpful for me",
    "relative_time": "3 months ago",
    "profile_image_url": "https://lh3.googleusercontent.com/a-/ALV-UjVykOS73Ra-xJpWKwGLTLkbxjavxxelvCtU2Mem1_XdKwMrj4-U=w54-h54-p-rp-mo-br100"
  },
  {
    "author": "Saparshini Murugesan",
    "rating": 5,
    "review_text": "Its nice coaching center",
    "relative_time": "2 years ago",
    "profile_image_url": "https://lh3.googleusercontent.com/a-/ALV-UjXF-URxXWp2vISprvaOHAff-rJkPyprPqT-BypSmtUh-gbLKlg=w54-h54-p-rp-mo-br100"
  },
  {
    "author": "Harish Anand",
    "rating": 5,
    "review_text": "Good place to learn",
    "relative_time": "6 years ago",
    "profile_image_url": "https://lh3.googleusercontent.com/a/ACg8ocIlmzQeydSxUNctsR2LLv-PHaY3FQYt2ZAWIa6xS-389mZ2Lsg=w54-h54-p-rp-mo-br100"
  },
  {
    "author": "Poonam Devi",
    "rating": 5,
    "review_text": "Excellent coaching",
    "relative_time": "6 months ago",
    "profile_image_url": "https://lh3.googleusercontent.com/a/ACg8ocKcAUdDdDAbYU7nlK0oavVZN6IKCnfQU-JgLYvJZ5cENIiglw=w54-h54-p-rp-mo-br100"
  },
  {
    "author": "SUDHA JAYA",
    "rating": 5,
    "review_text": "Superb coaching",
    "relative_time": "8 months ago",
    "profile_image_url": "https://lh3.googleusercontent.com/a/ACg8ocKr3_bUI6bLW3qN1Od0NFlPiTy5nBVnJw3cLVOmLPtqGFilsw=w54-h54-p-rp-mo-br100"
  },
  {
    "author": "Pavithra M",
    "rating": 5,
    "review_text": "Good academy for students",
    "relative_time": "8 months ago",
    "profile_image_url": "https://lh3.googleusercontent.com/a/ACg8ocJScCLO4nh6tkij68d9LmxGMESATc1T5_i2m6zgw7n4_XULSvI=w54-h54-p-rp-mo-br100"
  },
  {
    "author": "Bhuvana Narayanan",
    "rating": 5,
    "review_text": "Great coaching and mentoring",
    "relative_time": "7 years ago",
    "profile_image_url": "https://lh3.googleusercontent.com/a/ACg8ocLQIqEM0tgu_OKiHsfsD7p3oBB2_OSjzm36p0LviRpyq3vqYQg=w54-h54-p-rp-mo-br100"
  },
  {
    "author": "Prema DARSHAN",
    "rating": 5,
    "review_text": "Good education for children",
    "relative_time": "1 year ago",
    "profile_image_url": "https://lh3.googleusercontent.com/a-/ALV-UjW1xpIFSMlXn0ekk0kyFD1CA3EZPy4Iym6_B2TaV9i8C_88A_Zk=w54-h54-p-rp-mo-br100"
  }
]